calendar_base/__init__.py
calendar_base-0.0.1.dist-info/METADATA
calendar_base-0.0.1.dist-info/WHEEL
calendar_base-0.0.1.dist-info/top_level.txt
calendar_base-0.0.1.dist-info/RECORD
