Metadata-Version: 2.1
Name: calendar-base
Version: 0.0.1
Summary: A package to help organize calendar events
Home-page: https://github.com/GrantGMiller/flask_dictabase
Author: Grant miller
Author-email: grant@grant-miller.com
License: PSF
Project-URL: Source Code, https://github.com/GrantGMiller/flask_dictabase
Keywords: grant miller calendar base office365 google calendar
Platform: UNKNOWN
